Metadata-Version: 1.0
Name: pdfconduit-utils
Version: 1.1.2
Summary: PDF toolkit for preparing documents for distribution.
Home-page: https://github.com/mrstephenneal/pdfconduit
Author: Stephen Neal
Author-email: stephen@stephenneal.net
License: UNKNOWN
Platform: UNKNOWN
